ai_tools/__init__.py
ai_tools/utils.py
useful_ai_tools-0.1.0.dist-info/LICENSE
useful_ai_tools-0.1.0.dist-info/METADATA
useful_ai_tools-0.1.0.dist-info/WHEEL
useful_ai_tools-0.1.0.dist-info/top_level.txt
useful_ai_tools-0.1.0.dist-info/RECORD
