Metadata-Version: 2.2
Name: useful-ai-tools
Version: 0.1.0
Summary: A sample Python package for AI tools
Author: mohammad khalili
Author-email: mohammad.khalili1515@gmail.com
Requires-Python: >=3.6
License-File: LICENSE
Dynamic: author
Dynamic: author-email
Dynamic: requires-python
Dynamic: summary
